[
  {
    "id": "info",
    "title": "Информация о компании",
    "type": "text",
    "content": "Добро пожаловать! Это текстовая информация о компании. Здесь можно описать услуги, контакты и т.д."
  },
  {
    "id": "terms",
    "title": "Условия предоставления услуг",
    "type": "text",
    "content": "Текст условий. Пользователь соглашается с правилами при регистрации."
  },
  {
    "id": "guide",
    "title": "Руководство по консультациям",
    "type": "file",
    "path": "docs/guide.pdf"
  },
  {
    "id": "contract",
    "title": "Пример договора",
    "type": "file",
    "path": "docs/contract.docx"
  }
]